zspy/__build_num__.py
zspy/__init__.py
zspy/actor.py
zspy/impl/env_config.py
zspy/impl/env_config_cocotb.py
zspy/impl/env_config_provider.py
zspy/impl/loader.py
zuspec_py-0.0.3.8422382174.dist-info/LICENSE
zuspec_py-0.0.3.8422382174.dist-info/METADATA
zuspec_py-0.0.3.8422382174.dist-info/WHEEL
zuspec_py-0.0.3.8422382174.dist-info/top_level.txt
zuspec_py-0.0.3.8422382174.dist-info/RECORD
