Metadata-Version: 2.1
Name: zuspec-py
Version: 0.0.3.8422382174
Summary: Co-specification of hardware, software, design, and test behavior
Home-page: https://github.com/zuspec/zuspec
Author: Matthew Ballance
Author-email: matt.ballance@gmail.com
License: Apache 2.0
Keywords: PSS,Functional Verification,RTL,Verilog,SystemVerilog
License-File: LICENSE
Requires-Dist: pytypeworks
Requires-Dist: pyvsc-dataclasses
Requires-Dist: zuspec-dataclasses
Requires-Dist: vsc-solvers
Requires-Dist: zuspec-arl-dm
Requires-Dist: zuspec-arl-eval
Requires-Dist: zuspec-be-py
Requires-Dist: zuspec-fe-parser
Requires-Dist: zuspec-parser
